MANIFEST.in
README.txt
setup.cfg
setup.py
docs/HISTORY.txt
docs/INSTALL.txt
docs/LICENSE.GPL
docs/LICENSE.txt
redomino/__init__.py
redomino/__init__.pyc
redomino.social.egg-info/PKG-INFO
redomino.social.egg-info/SOURCES.txt
redomino.social.egg-info/dependency_links.txt
redomino.social.egg-info/entry_points.txt
redomino.social.egg-info/namespace_packages.txt
redomino.social.egg-info/not-zip-safe
redomino.social.egg-info/requires.txt
redomino.social.egg-info/top_level.txt
redomino/social/__init__.py
redomino/social/configure.zcml
redomino/social/browser/__init__.py
redomino/social/browser/configure.zcml
redomino/social/browser/interfaces.py
redomino/social/controlpanel/__init__.py
redomino/social/controlpanel/configure.zcml
redomino/social/controlpanel/likes.py
redomino/social/portlets/__init__.py
redomino/social/portlets/configure.zcml
redomino/social/portlets/socialportlet.pt
redomino/social/portlets/socialportlet.py
redomino/social/profiles/default/browserlayer.xml
redomino/social/profiles/default/metadata.xml
redomino/social/profiles/default/portlets.xml
redomino/social/profiles/default/propertiestool.xml
redomino/social/profiles/default/viewlets.xml
redomino/social/tests/__init__.py
redomino/social/tests/base.py
redomino/social/tests/test_portlet.py