Metadata-Version: 1.0
Name: redomino.social
Version: 1.2
Summary: Enhances sc.social.like with a portlet and others social plugins.
Home-page: https://github.com/redomino/redomino.social
Author: Andrea D'Este
Author-email: andrea.deste@redomino.com
License: GPL
Platform: UNKNOWN
Classifier: Framework :: Plone
Classifier: Programming Language :: Python
